genetk/enrich/__init__.py
genetk/enrich/gsea_py.py
genetk/network/__init__.py
genetk/network/network.py
genetk/prepmagma/__init__.py
genetk/prepmagma/mk_db.py
genetk/prepmagma/mk_geneset.py
genetk-0.1.0.dist-info/METADATA
genetk-0.1.0.dist-info/WHEEL
genetk-0.1.0.dist-info/top_level.txt
genetk-0.1.0.dist-info/RECORD
